{"cameraMode":{"drawMode":0,"name":"Shaded","section":"Shading Mode"},"sceneLighting":true,"audioPlay":false,"sceneViewState":{"m_AlwaysRefresh":false,"showFog":true,"showSkybox":true,"showFlares":true,"showImageEffects":true,"showParticleSystems":true,"showVisualEffectGraphs":true,"m_FxEnabled":true},"in2DMode":false,"pivot":{"x":-2.3098549842834474,"y":40.89554214477539,"z":14.211817741394043},"rotation":{"x":-0.06625423580408097,"y":-0.015866804867982866,"z":0.0010575354099273682,"w":-0.9976871013641357},"size":2.630892038345337,"orthographic":false}